otama
