Metadata-Version: 1.1
Name: otamapy
Version: 0.3.2
Summary: otamapy is Python Interface for otama.
Home-page: https://github.com/hhatto/otamapy
Author: Hideo Hattori
Author-email: hhatto.jp@gmail.com
License: GPLv3
Keywords: otama,CBIR
Platform: Linux
Classifier: Development Status :: 4 - Beta
Classifier: License :: OSI Approved :: GNU General Public License v3 (GPLv3)
Classifier: Operating System :: POSIX :: Linux
Classifier: Programming Language :: C
Classifier: Programming Language :: Python
Classifier: Programming Language :: Python :: 2
Classifier: Programming Language :: Python :: 3
